OCTVol/OCTVol.py
OCTVol/__init__.py
oct_vol-0.2.0.dist-info/LICENSE.txt
oct_vol-0.2.0.dist-info/METADATA
oct_vol-0.2.0.dist-info/WHEEL
oct_vol-0.2.0.dist-info/top_level.txt
oct_vol-0.2.0.dist-info/RECORD
