Metadata-Version: 2.1
Name: oct-vol
Version: 0.2.0
Summary: A package to read, write, and crop OCT .vol files.
Home-page: https://github.com/neurodial/oct-vol.git
Author: Amir Motamedi
Author-email: seyedamirhosein.motamedi@charite.de
License: UNKNOWN
Platform: UNKNOWN
Classifier: Development Status :: 4 - Beta
Classifier: Intended Audience :: Science/Research
Classifier: License :: OSI Approved :: MIT License
Classifier: Natural Language :: English
Classifier: Programming Language :: Python :: 3
Requires-Python: >=3.5
License-File: LICENSE.txt
Requires-Dist: numpy
